README.rst
setup.py
biwrap/__init__.py
biwrap.egg-info/PKG-INFO
biwrap.egg-info/SOURCES.txt
biwrap.egg-info/dependency_links.txt
biwrap.egg-info/top_level.txt