Metadata-Version: 1.1
Name: biwrap
Version: 0.1.3
Summary: Yet simple util to make wrapper with optional arguments
Home-page: https://github.com/ferrine/biwrap
Author: Maxim Kochurov
Author-email: maxim.v.kochurov@gmail.com
License: Copyright 2018 <Maxim Kochurov>
